bdd_tags_processor/__init__.py
bdd_tags_processor/bdd_tags_expression_processor.py
bdd_tags_processor-0.2.2.dist-info/METADATA
bdd_tags_processor-0.2.2.dist-info/WHEEL
bdd_tags_processor-0.2.2.dist-info/entry_points.txt
bdd_tags_processor-0.2.2.dist-info/top_level.txt
bdd_tags_processor-0.2.2.dist-info/RECORD
