Metadata-Version: 2.4
Name: bdd_tags_processor
Version: 0.2.2
Summary: Filter Cucumber BDD Feature files based on Scenario Tag expressions
Home-page: https://github.com/qarampage/bdd-tags-processor
Author: QA Rampage
Author-email: 16265665+qarampage@users.noreply.github.co
License: GPL-3.0-or-later
Keywords: bdd cucumber tag expression processor filter feature files
Classifier: Programming Language :: Python :: 3.9
Dynamic: author
Dynamic: author-email
Dynamic: classifier
Dynamic: description
Dynamic: description-content-type
Dynamic: home-page
Dynamic: keywords
Dynamic: license
Dynamic: summary
